{
  "billboard": {
    "dojos": "http://localhost:3000/dojos"
  },
  "dojos": [
    {
      "id": 8,
      "label": "2016-05-01 Air",
      "state": "past",
      "dojoType": "cluedo",
      "teamsUrl": "http://localhost:3000/dojos/8/teams/?_embed=members",
      "eventsUrl": "http://localhost:3000/dojos/8/events",
      "pointHistoryUrl": "http://localhost:3000/points/8"
    },
    {
      "id": 9,
      "label": "2016-05-02 US Presidents",
      "state": "past",
      "dojoType": "minesweeper",
      "teamsUrl": "http://localhost:3000/dojos/9/teams/?_embed=members",
      "eventsUrl": "http://localhost:3000/dojos/9/events",
      "pointHistoryUrl": "http://localhost:3000/points/9"
    },
    {
      "id": 11,
      "label": "2016-10-29 US States",
      "state": "running",
      "dojoType": "cluedo",
      "teamsUrl": "http://localhost:3000/dojos/11/teams/?_embed=members",
      "eventsUrl": "http://localhost:3000/dojos/11/events",
      "pointHistoryUrl": "http://localhost:3000/points/11"
    },
    {
      "id": 12,
      "label": "2016-12-13 Luca",
      "state": "running",
      "dojoType": "cluedo",
      "teamsUrl": "http://localhost:3000/dojos/12/teams/?_embed=members",
      "eventsUrl": "http://localhost:3000/dojos/12/events",
      "pointHistoryUrl": "http://localhost:3000/points/12"
    }
  ],
  "members": [
    {
      "teamId": 1,
      "status": "captain",
      "name": "karandit"
    },
    {
      "teamId": 1,
      "status": "crew",
      "name": "bublag"
    },
    {
      "teamId": 1,
      "status": "entrant",
      "name": "bali182"
    },
    {
      "teamId": 2,
      "status": "captain",
      "name": "bublag"
    },
    {
      "teamId": 3,
      "status": "captain",
      "name": "bali182"
    },
    {
      "teamId": 4,
      "status": "captain",
      "name": "zeldan"
    },
    {
      "teamId": 5,
      "status": "captain",
      "name": "schjan79"
    },
    {
      "teamId": 6,
      "status": "captain",
      "name": "zsozsogit"
    },
    {
      "teamId": 7,
      "status": "captain",
      "name": "zsozsogit"
    },
    {
      "teamId": 8,
      "status": "captain",
      "name": "zsozsogit"
    },
    {
      "teamId": 9,
      "status": "captain",
      "name": "zsozsogit"
    },
    {
      "teamId": 10,
      "status": "captain",
      "name": "zsozsogit"
    },
    {
      "teamId": 11,
      "status": "captain",
      "name": "zsozsogit"
    },
    {
      "teamId": 12,
      "status": "captain",
      "name": "zsozsogit"
    },
    {
      "teamId": 13,
      "status": "captain",
      "name": "karandit"
    },
    {
      "teamId": 14,
      "status": "captain",
      "name": "zsozsogit"
    },
    {
      "teamId": 15,
      "status": "captain",
      "name": "zeldan"
    },
    {
      "teamId": 16,
      "status": "captain",
      "name": "bali182"
    },
    {
      "teamId": 17,
      "status": "captain",
      "name": "schjan79"
    },
    {
      "teamId": 18,
      "status": "captain",
      "name": "bublag"
    }
  ],
  "teams": [
    {
      "id": 1,
      "dojoId": 8,
      "name": "Alpha",
      "descr": "ver 0.1",
      "points": 145
    },
    {
      "id": 2,
      "dojoId": 8,
      "name": "Bravo",
      "descr": "ver 0.100",
      "points": 68
    },
    {
      "id": 3,
      "dojoId": 8,
      "name": "Charlie",
      "descr": "ver 0.3",
      "points": 362
    },
    {
      "id": 4,
      "dojoId": 8,
      "name": "Delta",
      "descr": "blabla",
      "points": 68
    },
    {
      "id": 5,
      "dojoId": 8,
      "name": "Echo",
      "descr": "ver 0.6",
      "points": 21
    },
    {
      "id": 6,
      "dojoId": 8,
      "name": "Foxtrot",
      "descr": "ver 0.1.99",
      "points": 247
    },
    {
      "id": 7,
      "dojoId": 9,
      "name": "Washington",
      "descr": "ver first",
      "points": 45
    },
    {
      "id": 8,
      "dojoId": 9,
      "name": "Jefferson",
      "descr": "ver 0.100",
      "points": 24
    },
    {
      "id": 9,
      "dojoId": 9,
      "name": "Lincoln",
      "descr": "ver 0.3",
      "points": 11
    },
    {
      "id": 10,
      "dojoId": 9,
      "name": "Grant",
      "descr": "blabla",
      "points": 101
    },
    {
      "id": 11,
      "dojoId": 9,
      "name": "Roosevelt",
      "descr": "ver 0.6",
      "points": 37
    },
    {
      "id": 12,
      "dojoId": 9,
      "name": "Kennedy",
      "descr": "ver 0.1.99",
      "points": 57
    },
    {
      "id": 13,
      "dojoId": 11,
      "name": "Alabama",
      "descr": "ver first",
      "points": 201
    },
    {
      "id": 14,
      "dojoId": 11,
      "name": "Connecticut",
      "descr": "ver 0.100",
      "points": 310
    },
    {
      "id": 15,
      "dojoId": 11,
      "name": "Florida",
      "descr": "ver 0.3",
      "points": 109
    },
    {
      "id": 16,
      "dojoId": 11,
      "name": "Nebraska",
      "descr": "blabla",
      "points": 156
    },
    {
      "id": 17,
      "dojoId": 11,
      "name": "Oklahoma",
      "descr": "ver 0.6",
      "points": 210
    },
    {
      "id": 18,
      "dojoId": 11,
      "name": "Utah",
      "descr": "ver 0.1.99",
      "points": 315
    }
  ],
  "points": [
    {
      "id": 8,
      "games": [
        "M",
        "T",
        "W",
        "T",
        "F",
        "S",
        "S"
      ],
      "teams": [
        {
          "teamName": "Alpha",
          "data": [
            0,
            5,
            7,
            14,
            14,
            14,
            14
          ]
        },
        {
          "teamName": "Bravo",
          "data": [
            0,
            5,
            5,
            12,
            13,
            20,
            21
          ]
        },
        {
          "teamName": "Charlie",
          "data": [
            0,
            3,
            3,
            3,
            3,
            4,
            21
          ]
        },
        {
          "teamName": "Delta",
          "data": [
            0,
            7,
            8,
            8,
            9,
            10,
            10
          ]
        },
        {
          "teamName": "Echo",
          "data": [
            0,
            3,
            3,
            3,
            3,
            3,
            4
          ]
        },
        {
          "teamName": "Foxtrot",
          "data": [
            0,
            1,
            1,
            1,
            1,
            1,
            1
          ]
        }
      ]
    },
    {
      "id": 9,
      "games": [
        "M",
        "T",
        "W",
        "T",
        "F",
        "S",
        "S"
      ],
      "teams": [
        {
          "teamName": "Washington",
          "data": [
            0,
            5,
            7,
            14,
            14,
            14,
            14
          ]
        },
        {
          "teamName": "Jefferson",
          "data": [
            0,
            5,
            5,
            12,
            13,
            20,
            21
          ]
        },
        {
          "teamName": "Lincoln",
          "data": [
            0,
            1,
            3,
            3,
            3,
            4,
            21
          ]
        },
        {
          "teamName": "Grant",
          "data": [
            0,
            7,
            8,
            8,
            9,
            10,
            10
          ]
        },
        {
          "teamName": "Roosevelt",
          "data": [
            0,
            3,
            3,
            3,
            3,
            3,
            4
          ]
        },
        {
          "teamName": "Kennedy",
          "data": [
            0,
            1,
            1,
            1,
            1,
            1,
            1
          ]
        }
      ]
    },
    {
      "id": 11,
      "games": [
        "M",
        "T",
        "W",
        "T",
        "F",
        "S",
        "S"
      ],
      "teams": [
        {
          "teamName": "Alabama",
          "data": [
            0,
            5,
            7,
            14,
            14,
            14,
            14
          ]
        },
        {
          "teamName": "Connecticut",
          "data": [
            0,
            5,
            5,
            12,
            13,
            20,
            21
          ]
        },
        {
          "teamName": "Florida",
          "data": [
            0,
            2,
            3,
            3,
            3,
            4,
            21
          ]
        },
        {
          "teamName": "Nebraska",
          "data": [
            0,
            7,
            8,
            8,
            9,
            10,
            10
          ]
        },
        {
          "teamName": "Oklahoma",
          "data": [
            0,
            3,
            3,
            3,
            3,
            3,
            4
          ]
        },
        {
          "teamName": "Utah",
          "data": [
            0,
            1,
            1,
            1,
            1,
            1,
            1
          ]
        }
      ]
    },
    {
      "id": 12,
      "games": [],
      "teams": []
    }
  ],
  "events": [
    {
      "gameWonBy": 1,
      "dojoId": 8,
      "gameUrl": "http://localhost:3000/games/801"
    },
    {
      "gameWonBy": 1,
      "dojoId": 9,
      "gameUrl": "http://localhost:3000/games/901"
    }
  ],
  "games": [
    {
      "id": 801,
      "secret": {
        "weapon": "Revolver",
        "location": "Kitchen",
        "person": "ColMustard"
      },
      "bots": [
        {
          "teamName": "Alpha",
          "weapons": [
            "Candlestick",
            "IcePick"
          ],
          "locations": [
            "Billiards"
          ],
          "persons": []
        },
        {
          "teamName": "Bravo",
          "weapons": [
            "Poison"
          ],
          "locations": [
            "Conservatory",
            "Library"
          ],
          "persons": []
        },
        {
          "teamName": "Charlie",
          "weapons": [],
          "locations": [
            "Lounge"
          ],
          "persons": [
            "MrsWhite",
            "MsPeacock"
          ]
        },
        {
          "teamName": "Delta",
          "weapons": [
            "Poker"
          ],
          "locations": [
            "Stairs"
          ],
          "persons": [
            "MsScarlett"
          ]
        },
        {
          "teamName": "Echo",
          "weapons": [],
          "locations": [
            "Studio",
            "BedRoom"
          ],
          "persons": [
            "ProfPlum"
          ]
        },
        {
          "teamName": "Foxtrot",
          "weapons": [
            "Shears"
          ],
          "locations": [
            "TrophyHall"
          ],
          "persons": [
            "RevGreen"
          ]
        }
      ],
      "rounds": [
        {
          "asked": {
            "by": "Alpha",
            "question": {
              "weapon": "Poker",
              "location": "Studio",
              "person": "RevGreen"
            }
          },
          "answered": [
            {
              "by": "Bravo",
              "answer": null
            },
            {
              "by": "Charlie",
              "answer": null
            },
            {
              "by": "Delta",
              "answer": "Poker"
            }
          ]
        },
        {
          "asked": {
            "by": "Bravo",
            "question": {
              "weapon": "Poison",
              "location": "Studio",
              "person": "ProfPlum"
            }
          },
          "answered": [
            {
              "by": "Charlie",
              "answer": null
            },
            {
              "by": "Delta",
              "answer": null
            },
            {
              "by": "Echo",
              "answer": null
            },
            {
              "by": "Foxtrot",
              "answer": null
            },
            {
              "by": "Alpha",
              "answer": "Studio"
            }
          ]
        },
        {
          "accused": {
            "by": "Charlie",
            "question": {
              "weapon": "Poker",
              "location": "Studio",
              "person": "RevGreen"
            }
          },
          "answer": true
        }
      ]
    },
    {
      "id": 901,
      "board": "let's play"
    }
  ]
}
